complete_metadata/__init__.py
complete_metadata/mixins.py
drf_complete_metadata-1.0.0.dist-info/LICENSE
drf_complete_metadata-1.0.0.dist-info/METADATA
drf_complete_metadata-1.0.0.dist-info/WHEEL
drf_complete_metadata-1.0.0.dist-info/top_level.txt
drf_complete_metadata-1.0.0.dist-info/RECORD
