Metadata-Version: 2.1
Name: drf-complete-metadata
Version: 1.0.0
Summary: This package provides custom metadata class for Django Rest Framework to enrich data returned by OPTIONS requests in easy way.
Author: IIIT
Author-email: github@iiit.pl
License: UNKNOWN
Platform: UNKNOWN
Classifier: Environment :: Web Environment
Classifier: Framework :: Django
Classifier: Intended Audience :: Developers
Classifier: Operating System :: OS Independent
Classifier: Programming Language :: Python
Classifier: Programming Language :: Python :: 3.6
Classifier: Programming Language :: Python :: 3.7
Classifier: Programming Language :: Python :: 3.8
Classifier: Programming Language :: Python :: 3.9
License-File: LICENSE
Requires-Dist: Django (<3.0,>=1.11)
Requires-Dist: djangorestframework (>=3.6.4)
